.gitignore
README.md
changelog.md
setup.py
examples/basic_usage.py
pymiecs/__init__.py
pymiecs/main.py
pymiecs/materials.py
pymiecs/mie_coeff.py
pymiecs/special.py
pymiecs/t_matrix.py
pymiecs/tools.py
pymiecs.egg-info/PKG-INFO
pymiecs.egg-info/SOURCES.txt
pymiecs.egg-info/dependency_links.txt
pymiecs.egg-info/requires.txt
pymiecs.egg-info/top_level.txt
pymiecs/data/Ag_Johnson1972.yml
pymiecs/data/Al2O3e_Malitson1972.yml
pymiecs/data/Al2O3o_Malitson1972.yml
pymiecs/data/Al_Rakic1995.yml
pymiecs/data/Au_Johnson1972.yml
pymiecs/data/GaAs_Papatryfonos2021.yml
pymiecs/data/GaN_Kawashima1997.yml
pymiecs/data/GaP_Aspnes1983.yml
pymiecs/data/Ge_Nunley2016.yml
pymiecs/data/InAs_Aspnes1983.yml
pymiecs/data/InP_Aspnes1983.yml
pymiecs/data/Si3N4_Luke2015.yml
pymiecs/data/SiO2_Malitson1965.yml
pymiecs/data/Si_Schinke2015.yml
pymiecs/data/TiO2_Devore1965.yml
pymiecs/data/ZrO2_Wood1982.yml
pymiecs/data/aSi_Pierce1972.yml
scripts/mie_coreshell_equations_sympy.py
scripts/test_own_coreshell_tmatrix_smuthi.py
scripts/test_script.py
tests/test_coeff.py
tests/test_scat.py