Metadata-Version: 2.1
Name: pymiecs
Version: 0.5
Summary: A simple python Mie solver for core-shell nano-spheres.
Home-page: https://gitlab.com/wiechapeter/pymiecs
Download-URL: 
Author: Peter R. Wiecha
Author-email: pwiecha@laas.fr
License: GPLv3+
Keywords: Mie theory,core shell nanospheres,effective polarizabilities,electrodynamical simulations,nano optics
Classifier: Development Status :: 5 - Production/Stable
Classifier: Topic :: Scientific/Engineering :: Physics
Classifier: Environment :: Console
Classifier: Programming Language :: Python :: 3.9
Classifier: Programming Language :: Python :: 3.10
Classifier: Programming Language :: Python :: 3.11
Classifier: Programming Language :: Python :: 3.12
Classifier: License :: OSI Approved :: GNU General Public License v3 or later (GPLv3+)
Classifier: Intended Audience :: Science/Research
Requires-Python: >=3.9
Requires-Dist: scipy
Requires-Dist: numpy
